waveshare_epd_driver.py
circuitpython_waveshare_epd-0.0.1.dist-info/LICENSE
circuitpython_waveshare_epd-0.0.1.dist-info/METADATA
circuitpython_waveshare_epd-0.0.1.dist-info/WHEEL
circuitpython_waveshare_epd-0.0.1.dist-info/top_level.txt
circuitpython_waveshare_epd-0.0.1.dist-info/RECORD
