Metadata-Version: 2.1
Name: circuitpython-waveshare-epd
Version: 0.0.1
Summary: CircuitPython `displayio` drivers for Waveshare-based ePaper displays
Author-email: Falco Gerritsjans <contact@falco.pro>
License: MIT
Project-URL: Homepage, https://github.com/FalcoG/CircuitPython_Waveshare_EPD
Keywords: blinka,circuitpython,micropython,2in66b,waveshare,displayio,epd,epaper
Classifier: Intended Audience :: Developers
Classifier: Topic :: Software Development :: Libraries
Classifier: Topic :: Software Development :: Embedded Systems
Classifier: Topic :: System :: Hardware
Classifier: License :: OSI Approved :: MIT License
Classifier: Programming Language :: Python :: 3
License-File: LICENSE
Requires-Dist: Adafruit-Blinka
Provides-Extra: optional
